scriptd/__init__.py
scriptd/app/__init__.py
scriptd/app/exceptions.py
scriptd/app/flask_helper.py
scriptd/app/handler.py
scriptd/app/protocol.py
scriptd/app/util.py
scriptd/cli/__init__.py
scriptd/cli/client.py
scriptd/cli/server.py
scriptd-0.5.1.dist-info/METADATA
scriptd-0.5.1.dist-info/RECORD
scriptd-0.5.1.dist-info/WHEEL
scriptd-0.5.1.dist-info/entry_points.txt
scriptd-0.5.1.dist-info/top_level.txt
