Metadata-Version: 2.1
Name: scriptd
Version: 0.5.1
Summary: Scriptd lets you execute a set of preconfigured scripts or executables via HTTP API, securely, without exposing terminal access, and with almost no configurations.
Home-page: https://github.com/jasonszang/scriptd
Author: jasonszang
Author-email: jasonszang@126.com
License: MIT
Platform: UNKNOWN
Classifier: Programming Language :: Python :: 2.7
Classifier: Programming Language :: Python :: 3
Classifier: Programming Language :: Python :: 3.3
Classifier: Programming Language :: Python :: 3.4
Classifier: Programming Language :: Python :: 3.5
Classifier: Programming Language :: Python :: 3.6
Classifier: Programming Language :: Python :: 3.7
Classifier: Operating System :: OS Independent
Requires-Dist: cryptography (>=2.0)
Requires-Dist: flask (>=0.12.1)
Requires-Dist: six (>=1.9)
Requires-Dist: typing (>=3.6.1)
Requires-Dist: requests (>=2.0.0)
